LICENSE
MANIFEST.in
README.md
setup.cfg
setup.py
django_rest_magic.egg-info/PKG-INFO
django_rest_magic.egg-info/SOURCES.txt
django_rest_magic.egg-info/dependency_links.txt
django_rest_magic.egg-info/requires.txt
django_rest_magic.egg-info/top_level.txt
docs/Makefile
docs/conf.py
docs/index.rst
docs/make.bat
docs/areas/authorization.rst
docs/areas/serializers.rst
docs/areas/viewsets.rst
docs/dev/contributing.rst
drf_magic/__init__.py
drf_magic/admin.py
drf_magic/apps.py
drf_magic/decorators.py
drf_magic/fields.py
drf_magic/filtersets.py
drf_magic/pagination.py
drf_magic/permissions.py
drf_magic/routers.py
drf_magic/settings.py
drf_magic/test.py
drf_magic/utils.py
drf_magic/access/__init__.py
drf_magic/access/accessors.py
drf_magic/access/apps.py
drf_magic/access/patch.py
drf_magic/access/signals.py
drf_magic/docs/__init__.py
drf_magic/docs/generators.py
drf_magic/docs/schema.py
drf_magic/docs/urls.py
drf_magic/migrations/0001_initial.py
drf_magic/migrations/__init__.py
drf_magic/models/__init__.py
drf_magic/models/mixins.py
drf_magic/serializers/__init__.py
drf_magic/serializers/loader.py
drf_magic/serializers/viewsets.py
drf_magic/views/__init__.py
drf_magic/views/mixins.py